lnschema_wetlab/__init__.py
lnschema_wetlab/_actual.py
lnschema_wetlab/_core.py
lnschema_wetlab/_link.py
lnschema_wetlab/link.py
lnschema_wetlab/dev/__init__.py
lnschema_wetlab/dev/_id.py
lnschema_wetlab/dev/_sample_submission.py
lnschema_wetlab/dev/_versions.py
lnschema_wetlab/dev/id.py
lnschema_wetlab/dev/datasets/__init__.py
lnschema_wetlab/dev/datasets/_core.py
lnschema_wetlab/migrations/versions/2022-10-14-3ed88d3699fd-v0_6_0.py
lnschema_wetlab/migrations/versions/2022-10-19-01360b6492cc-v0_7_0.py
lnschema_wetlab/migrations/versions/2022-10-19-05efb2ed6192-v0_6_0.post1.py
lnschema_wetlab/migrations/versions/2022-10-19-a171e861e473-v0_7_1.py
lnschema_wetlab/migrations/versions/2022-10-19-e2507b7564f0-v0_7_0.post1.py
lnschema_wetlab/migrations/versions/2022-10-20-a5d6b07f1401-v0_7_2.py
lnschema_wetlab/migrations/versions/2022-11-03-bfda12fc80a8-v0_8_0.py
lnschema_wetlab-0.14.0.dist-info/LICENSE
lnschema_wetlab-0.14.0.dist-info/WHEEL
lnschema_wetlab-0.14.0.dist-info/METADATA
lnschema_wetlab-0.14.0.dist-info/RECORD
