Metadata-Version: 2.1
Name: lnschema_wetlab
Version: 0.14.0
Summary: Base classes for a wetlab schema (`vvhc`).
Author-email: Lamin Labs <laminlabs@gmail.com>
Classifier: License :: OSI Approved :: Apache Software License
Classifier: Programming Language :: Python :: 3.8
Classifier: Programming Language :: Python :: 3.9
Classifier: Programming Language :: Python :: 3.10
Requires-Dist: nbproject
Requires-Dist: sqlmodel
Requires-Dist: lnschema_core>=0.24.1
Requires-Dist: lnschema_bionty>=0.10.1
Requires-Dist: lndb>=0.32.0
Requires-Dist: pre-commit ; extra == "dev"
Requires-Dist: nox ; extra == "dev"
Requires-Dist: pytest>=6.0 ; extra == "test"
Requires-Dist: pytest-cov ; extra == "test"
Requires-Dist: cloudpathlib ; extra == "test"
Project-URL: Home, https://github.com/laminlabs/lnschema-wetlab
Provides-Extra: dev
Provides-Extra: test
